README.rst
setup.py
scripts/fl-build-report
scripts/fl-credential-ctl
scripts/fl-install-demo
scripts/fl-monitor-ctl
scripts/fl-record
scripts/fl-run-bench
scripts/fl-run-test
src/funkload/BenchRunner.py
src/funkload/CredentialBase.py
src/funkload/CredentialFile.py
src/funkload/CredentialRandom.py
src/funkload/DemoInstaller.py
src/funkload/Distributed.py
src/funkload/FunkLoadDocTest.py
src/funkload/FunkLoadHTTPServer.py
src/funkload/FunkLoadTestCase.py
src/funkload/Lipsum.py
src/funkload/MergeResultFiles.py
src/funkload/Monitor.py
src/funkload/MonitorPlugins.py
src/funkload/MonitorPluginsDefault.py
src/funkload/PatchWebunit.py
src/funkload/Recorder.py
src/funkload/ReportBuilder.py
src/funkload/ReportRenderDiff.py
src/funkload/ReportRenderHtml.py
src/funkload/ReportRenderHtmlBase.py
src/funkload/ReportRenderHtmlGnuPlot.py
src/funkload/ReportRenderOrg.py
src/funkload/ReportRenderRst.py
src/funkload/ReportRenderTrend.py
src/funkload/ReportStats.py
src/funkload/TestRunner.py
src/funkload/XmlRpcBase.py
src/funkload/__init__.py
src/funkload/apdex.py
src/funkload/rtfeedback.py
src/funkload/utils.py
src/funkload.egg-info/PKG-INFO
src/funkload.egg-info/SOURCES.txt
src/funkload.egg-info/dependency_links.txt
src/funkload.egg-info/entry_points.txt
src/funkload.egg-info/requires.txt
src/funkload.egg-info/top_level.txt
src/funkload.egg-info/zip-safe
src/funkload/data/ConfigurationTestCase.tpl
src/funkload/data/MyFacesScriptTestCase.tpl
src/funkload/data/ScriptTestCase.tpl
src/funkload/data/funkload.css
src/funkload/demo/README.txt
src/funkload/demo/cmf/Cmf.conf
src/funkload/demo/cmf/README.txt
src/funkload/demo/cmf/credential.conf
src/funkload/demo/cmf/groups.txt
src/funkload/demo/cmf/passwords.txt
src/funkload/demo/cmf/test_Cmf.py
src/funkload/demo/cps/CPS338TestCase.py
src/funkload/demo/cps/CPS340DocTest.py
src/funkload/demo/cps/CPS340TestCase.py
src/funkload/demo/cps/CPSTestCase.py
src/funkload/demo/cps/ZopeTestCase.py
src/funkload/demo/seam-booking-1.1.5/Makefile
src/funkload/demo/seam-booking-1.1.5/README.txt
src/funkload/demo/seam-booking-1.1.5/SeamBooking.conf
src/funkload/demo/seam-booking-1.1.5/monitor.conf
src/funkload/demo/seam-booking-1.1.5/test_SeamBooking.py
src/funkload/demo/simple/Makefile
