Metadata-Version: 1.1
Name: funkload
Version: 1.17.1
Summary: Functional and load web tester.
Home-page: http://funkload.nuxeo.org/
Author: Benoit Delbosc
Author-email: bdelbosc@nuxeo.com
License: GPL
Download-URL: http://pypi.python.org/packages/source/f/funkload/funkload-1.17.1.tar.gz
Keywords: testing benching load performance functional monitoring
Platform: UNKNOWN
Classifier: Development Status :: 5 - Production/Stable
Classifier: Environment :: Console
Classifier: Intended Audience :: Developers
Classifier: Intended Audience :: System Administrators
Classifier: Natural Language :: English
Classifier: License :: OSI Approved :: GNU General Public License (GPL)
Classifier: Operating System :: OS Independent
Classifier: Programming Language :: Python
Classifier: Topic :: Internet :: WWW/HTTP :: Site Management
Classifier: Topic :: Software Development :: Testing
Classifier: Topic :: Software Development :: Quality Assurance
Classifier: Topic :: System :: Benchmark
Classifier: Topic :: System :: Monitoring
